helping/__init__.py
helping/helping.py
helping-0.0.5.dist-info/LICENSE
helping-0.0.5.dist-info/METADATA
helping-0.0.5.dist-info/WHEEL
helping-0.0.5.dist-info/top_level.txt
helping-0.0.5.dist-info/RECORD
