Metadata-Version: 2.1
Name: helping
Version: 0.0.5
Summary: Readable information for real people.
Home-page: https://github.com/ConquerProgramming1/helping
Author: Ronald Hayden
Author-email: ron@conquerprogramming.com
License: UNKNOWN
Platform: UNKNOWN
Classifier: Programming Language :: Python :: 3
Classifier: License :: OSI Approved :: MIT License
Classifier: Operating System :: OS Independent
